{
  "required" : [ "contactId", "feeId", "termId" ],
  "unevaluatedProperties" : false,
  "properties" : {
    "contactId" : {
      "title" : "contactId",
      "description" : "Contact Id of the student",
      "lightning:type" : "lightning__textType",
      "lightning:isPII" : false,
      "copilotAction:isUserInput" : false
    },
    "feeId" : {
      "title" : "feeId",
      "description" : "Fee ID",
      "lightning:type" : "lightning__textType",
      "lightning:isPII" : false,
      "copilotAction:isUserInput" : false
    },
    "termId" : {
      "title" : "termId",
      "description" : "Term ID",
      "lightning:type" : "lightning__textType",
      "lightning:isPII" : false,
      "copilotAction:isUserInput" : false
    }
  },
  "lightning:type" : "lightning__objectType"
}